{
  "topicId": "strat-3-2-2",
  "title": "管理会計",
  "pages": [
    {
      "pageNumber": 1,
      "title": "管理会計の目的と役割",
      "content": "## 管理会計とは\n\n管理会計は、企業内部の経営者や管理者が意思決定を行うために必要な会計情報を提供する仕組みです。財務会計が外部の利害関係者（株主、債権者など）への報告を目的とするのに対し、管理会計は内部管理を目的としています。\n\n## 管理会計の主な目的\n\n### 1. 経営意思決定の支援\n- 新製品の開発可否の判断\n- 設備投資の経済性評価\n- 製品ラインの廃止・継続の決定\n- 価格設定の根拠提供\n\n### 2. 業績評価と統制\n- 部門別の業績測定\n- 予算と実績の比較分析\n- 責任会計による評価\n- KPI（重要業績評価指標）の設定\n\n### 3. 計画立案の基礎情報提供\n- 予算編成のための原価情報\n- 中長期経営計画の策定支援\n- 資源配分の最適化\n\n## 財務会計との違い\n\n| 項目 | 財務会計 | 管理会計 |\n|------|----------|----------|\n| 目的 | 外部報告 | 内部管理 |\n| 対象者 | 株主、債権者、税務署 | 経営者、管理者 |\n| 法的規制 | あり（会社法、金融商品取引法） | なし（自由） |\n| 報告期間 | 定期（年次、四半期） | 必要に応じて随時 |\n| 範囲 | 企業全体 | 部門、製品、プロジェクト単位 |\n| 時間軸 | 過去志向 | 未来志向 |\n\n## ITシステムにおける管理会計の重要性\n\nIT企業やシステム開発プロジェクトにおいては、以下の点で管理会計が重要です：\n\n- **プロジェクト別原価計算**：各プロジェクトの収益性を正確に把握\n- **工数管理**：人的リソースのコスト配分と効率性評価\n- **クラウドサービスのコスト管理**：従量課金モデルにおける原価計算\n- **研究開発費の管理**：投資対効果の測定と意思決定"
    },
    {
      "pageNumber": 2,
      "title": "原価計算の基礎",
      "content": "## 原価計算とは\n\n原価計算は、製品やサービスを生産・提供するために発生したコストを計算し、集計する手法です。正確な原価情報は価格設定、収益性分析、在庫評価に不可欠です。\n\n## 原価の分類\n\n### 1. 形態別分類\n- **材料費**：製品の主要材料、補助材料、消耗品費\n- **労務費**：賃金、給料、福利厚生費\n- **経費**：減価償却費、電力費、外注費、その他\n\n### 2. 製品との関連による分類\n- **直接費**：特定の製品に直接紐づけられるコスト（直接材料費、直接労務費）\n- **間接費**：複数の製品に共通して発生するコスト（工場管理費、間接労務費）\n\n### 3. 操業度との関連による分類\n- **変動費**：生産量に比例して変動（材料費、電力費）\n- **固定費**：生産量に関わらず一定（減価償却費、管理者給与）\n\n## 個別原価計算\n\n受注生産や個別プロジェクトごとに原価を集計する方法です。\n\n### 適用例\n- システム開発プロジェクト\n- 建設工事\n- 造船\n- 特注機械製造\n\n### 計算手順\n\n1. **製造指図書の発行**：プロジェクト開始時に識別番号を付与\n2. **直接費の賦課**：プロジェクトに直接発生した費用を記録\n3. **間接費の配賦**：共通費用を一定の基準で各プロジェクトに配分\n4. **原価の集計**：プロジェクト完了時に総原価を計算\n\n### 具体例：システム開発プロジェクト\n\n**プロジェクトA（顧客管理システム開発）**\n\n- 直接材料費：サーバー機器 500,000円\n- 直接労務費：SE 5名 × 200時間 × 5,000円/時 = 5,000,000円\n- 直接経費：外注費 1,000,000円\n- 間接費配賦：工数比率で配賦 2,000,000円\n- **総原価：8,500,000円**\n\n## 総合原価計算\n\n大量生産において、一定期間の総原価を生産量で割って単位原価を求める方法です。\n\n### 適用例\n- 食品製造\n- 化学製品\n- 電子部品の大量生産\n- クラウドサービスの提供\n\n### 計算手順\n\n1. **期間原価の集計**：当月発生した全原価を集計\n2. **完成品換算量の計算**：仕掛品を完成品換算\n3. **単位原価の計算**：総原価 ÷ 完成品換算量\n4. **完成品と仕掛品への配分**\n\n### 具体例：SaaS製品の月額原価\n\n**当月データ**\n- サーバー費用：3,000,000円\n- 保守人件費：5,000,000円\n- その他経費：2,000,000円\n- **月間総原価：10,000,000円**\n- 契約ユーザー数：1,000社\n- **1社あたり月額原価：10,000円**\n\nこの情報から、適正な価格設定（例：月額15,000円）を判断できます。"
    },
    {
      "pageNumber": 3,
      "title": "ABC（活動基準原価計算）",
      "content": "## ABCとは\n\nABC（Activity Based Costing：活動基準原価計算）は、企業の活動（アクティビティ）を基準として間接費を配賦する原価計算手法です。従来の単純な配賦基準（労働時間や機械稼働時間）よりも、実態に即した正確な原価計算が可能になります。\n\n## 従来の原価計算の問題点\n\n### 例：製造業の間接費配賦\n\n**従来方式（直接労働時間で配賦）**\n\n| 製品 | 生産量 | 直接労務費 | 配賦された間接費 | 単位原価 |\n|------|--------|------------|------------------|----------|\n| 製品A（標準品） | 10,000個 | 10,000時間 | 50,000,000円 | 5,500円 |\n| 製品B（特注品） | 1,000個 | 2,000時間 | 10,000,000円 | 11,000円 |\n\nこの方法では、製品Bのような少量多品種生産品が必要とする以下のコストが反映されません：\n- 段取り替え作業\n- 品質検査\n- 発注・在庫管理\n- 設計変更対応\n\n## ABCの基本概念\n\n### コストドライバー\n\n活動のコストを引き起こす要因（コストドライバー）を特定し、それに基づいて配賦します。\n\n**主なコストドライバーの例**\n- 段取り回数\n- 検査回数\n- 受注件数\n- 設計変更回数\n- 出荷回数\n\n## ABCの計算手順\n\n### ステップ1：活動の識別\n\n企業の業務を活動単位に分解します。\n\n**例：製造業の主な活動**\n1. 資材調達活動\n2. 段取り活動\n3. 加工活動\n4. 品質検査活動\n5. 出荷活動\n\n### ステップ2：活動ごとのコスト集計\n\n各活動に発生するコストを集計します。\n\n| 活動 | コスト | コストドライバー |\n|------|--------|------------------|\n| 資材調達 | 12,000,000円 | 発注回数 |\n| 段取り | 15,000,000円 | 段取り回数 |\n| 加工 | 20,000,000円 | 機械時間 |\n| 品質検査 | 8,000,000円 | 検査回数 |\n| 出荷 | 5,000,000円 | 出荷回数 |\n\n### ステップ3：活動単価の計算\n\n活動単価 = 活動コスト ÷ コストドライバー総量\n\n**例**\n- 段取り活動単価 = 15,000,000円 ÷ 300回 = 50,000円/回\n- 検査活動単価 = 8,000,000円 ÷ 400回 = 20,000円/回\n\n### ステップ4：製品への原価配賦\n\n各製品が消費した活動量に基づいて配賦します。\n\n**製品A（標準品）**\n- 段取り：10回 × 50,000円 = 500,000円\n- 検査：50回 × 20,000円 = 1,000,000円\n\n**製品B（特注品）**\n- 段取り：100回 × 50,000円 = 5,000,000円\n- 検査：200回 × 20,000円 = 4,000,000円\n\n## ABCによる改善効果\n\n### 1. 正確な原価把握\n\n特注品や少量生産品の隠れたコストが明確になります。\n\n### 2. 価格設定の適正化\n\n製品Bのような特注品は、実際のコストに見合った価格設定が可能になります。\n\n### 3. 業務改善の指針\n\nコスト削減すべき活動が明確になります：\n- 段取り回数の削減（生産ロットの最適化）\n- 検査工程の効率化\n- 発注頻度の見直し\n\n### 4. 製品ミックスの最適化\n\n真の収益性に基づいた製品戦略の立案が可能です。\n\n## IT分野でのABC適用例\n\n**システム開発会社の例**\n\n活動とコストドライバー：\n- 要件定義活動：打ち合わせ回数\n- 設計活動：設計ドキュメント数\n- 開発活動：開発工数\n- テスト活動：テストケース数\n- 保守活動：問い合わせ件数\n\nこれにより、手間のかかる顧客や複雑なプロジェクトの真のコストが把握できます。"
    },
    {
      "pageNumber": 4,
      "title": "CVP分析（損益分岐点分析）",
      "content": "## CVP分析とは\n\nCVP分析（Cost-Volume-Profit analysis：原価・営業量・利益分析）は、売上高、コスト、利益の関係を分析し、経営意思決定に活用する手法です。特に損益分岐点の算出が重要です。\n\n## 基本概念\n\n### コストの分解\n\n総コスト = 固定費 + 変動費\n\n- **固定費（Fixed Cost）**：売上に関わらず一定（家賃、管理者給与、減価償却費）\n- **変動費（Variable Cost）**：売上に比例して変動（材料費、販売手数料）\n\n### 利益の計算式\n\n**利益 = 売上高 - 変動費 - 固定費**\n\nまたは\n\n**利益 = 売上高 × 限界利益率 - 固定費**\n\n### 重要な指標\n\n1. **限界利益**：売上高 - 変動費\n2. **限界利益率**：限界利益 ÷ 売上高 × 100\n3. **貢献利益**：限界利益と同義（固定費の回収に貢献する利益）\n\n## 損益分岐点の計算\n\n### 損益分岐点売上高\n\n利益がゼロになる売上高を求めます。\n\n**損益分岐点売上高 = 固定費 ÷ 限界利益率**\n\nまたは\n\n**損益分岐点売上高 = 固定費 ÷ (1 - 変動費率)**\n\n### 損益分岐点販売数量\n\n**損益分岐点販売数量 = 固定費 ÷ (単価 - 単位変動費)**\n\n## 具体例：SaaS企業のCVP分析\n\n### 前提条件\n\n- 月額サービス料金：10,000円/社\n- 顧客獲得時の変動費：3,000円/社（販売手数料、初期設定費用）\n- 月間固定費：30,000,000円（サーバー費、人件費、家賃など）\n\n### 計算\n\n**単位限界利益**\n= 10,000円 - 3,000円 = 7,000円\n\n**限界利益率**\n= 7,000円 ÷ 10,000円 = 0.7（70%）\n\n**損益分岐点販売数量**\n= 30,000,000円 ÷ 7,000円 = 4,286社（小数点切り上げ）\n\n**損益分岐点売上高**\n= 4,286社 × 10,000円 = 42,860,000円\n\n### 解釈\n\n月間4,286社以上の契約があれば黒字、それ以下なら赤字となります。\n\n## 目標利益の計算\n\n### 目標利益を達成する売上高\n\n**必要売上高 = (固定費 + 目標利益) ÷ 限界利益率**\n\n### 例：月間利益700万円を目指す場合\n\n**必要売上高**\n= (30,000,000円 + 7,000,000円) ÷ 0.7\n= 37,000,000円 ÷ 0.7\n= 52,857,143円\n\n**必要契約社数**\n= 52,857,143円 ÷ 10,000円 = 5,286社\n\n## 安全余裕率\n\n現在の売上高が損益分岐点をどれだけ上回っているかを示す指標です。\n\n**安全余裕率 = (実際売上高 - 損益分岐点売上高) ÷ 実際売上高 × 100**\n\n### 例：月間売上高6,000万円の場合\n\n**安全余裕率**\n= (60,000,000円 - 42,860,000円) ÷ 60,000,000円 × 100\n= 28.6%\n\n売上が28.6%減少しても赤字にならない余裕があることを示します。\n\n## CVP分析の活用場面\n\n### 1. 価格決定\n\n値下げによる販売数量増加と利益への影響を分析します。\n\n**例**\n- 現在：10,000円 × 5,000社 = 50,000,000円（利益5,000,000円）\n- 値下げ案：9,000円 × 6,000社 = 54,000,000円（利益？）\n\n**新限界利益率** = (9,000 - 3,000) ÷ 9,000 = 66.7%\n**新利益** = 54,000,000 × 0.667 - 30,000,000 = 6,018,000円\n\n→ 値下げで利益増加を確認できます。\n\n### 2. 固定費削減の効果測定\n\n固定費を10%削減（27,000,000円）した場合：\n\n**新損益分岐点**\n= 27,000,000円 ÷ 0.7 = 38,571,429円\n\n→ 約430万円の売上高減少まで耐えられます。\n\n### 3. 新規事業の採算性評価\n\n初期投資と損益分岐点到達時期を予測し、事業化判断に活用します。\n\n### 4. 製品ミックスの最適化\n\n複数製品の限界利益率を比較し、注力すべき製品を決定します。"
    },
    {
      "pageNumber": 5,
      "title": "予算管理と差異分析",
      "content": "## 予算管理とは\n\n予算管理は、企業の計画（予算）を設定し、実績と比較・分析することで、経営目標の達成を支援する管理手法です。PDCAサイクルの基盤となります。\n\n## 予算の種類\n\n### 1. 総合予算\n\n企業全体の包括的な予算体系です。\n\n- **売上予算**：販売計画に基づく収益予測\n- **製造予算**：生産計画に基づくコスト予測\n- **販売費予算**：営業活動に必要な経費\n- **一般管理費予算**：本社管理部門の経費\n- **資本予算**：設備投資計画\n- **キャッシュフロー予算**：資金繰り計画\n\n### 2. 部門別予算\n\n各部門の責任範囲に応じた予算です。\n\n- 営業部門：売上予算、販売費予算\n- 製造部門：製造原価予算\n- 開発部門：研究開発費予算\n- 管理部門：一般管理費予算\n\n## 予算編成のプロセス\n\n### ステップ1：経営方針の策定\n\n経営トップが中期経営計画に基づき、年度方針を示します。\n\n### ステップ2：予算方針の伝達\n\n予算編成の基本方針（売上目標、コスト削減率など）を各部門に通知します。\n\n### ステップ3：部門別予算の作成\n\n各部門が具体的な活動計画と予算を作成します。\n\n### ステップ4：予算の調整・承認\n\n部門間の調整、経営層による審査・承認を経て予算を確定します。\n\n### ステップ5：予算の配布と実行\n\n確定予算を各部門に配布し、実行を開始します。\n\n## 予算統制の方法\n\n### 月次予算実績管理\n\n毎月、予算と実績を比較し、差異を分析します。\n\n**予算実績対比表の例（IT企業の開発部門）**\n\n| 項目 | 年間予算 | 当月予算 | 当月実績 | 差異 | 差異率 | 累計予算 | 累計実績 | 累計差異 |\n|------|----------|----------|----------|------|--------|----------|----------|----------|\n| 売上高 | 600,000 | 50,000 | 48,000 | -2,000 | -4.0% | 300,000 | 295,000 | -5,000 |\n| 人件費 | 360,000 | 30,000 | 31,500 | 1,500 | 5.0% | 180,000 | 185,000 | 5,000 |\n| 外注費 | 120,000 | 10,000 | 9,500 | -500 | -5.0% | 60,000 | 58,000 | -2,000 |\n| 経費 | 60,000 | 5,000 | 5,200 | 200 | 4.0% | 30,000 | 31,000 | 1,000 |\n| 営業利益 | 60,000 | 5,000 | 1,800 | -3,200 | -64.0% | 30,000 | 21,000 | -9,000 |\n\n（単位：千円）\n\n## 差異分析\n\n予算と実績の差異を詳細に分析し、原因を特定します。\n\n### 売上高差異の分解\n\n**売上高差異 = 実際売上高 - 予算売上高**\n\nこれを以下に分解します：\n\n1. **価格差異** = (実際単価 - 予算単価) × 実際販売数量\n2. **数量差異** = (実際販売数量 - 予算販売数量) × 予算単価\n\n### 具体例：SaaS製品の売上差異分析\n\n**予算**\n- 契約単価：10,000円/月\n- 契約社数：5,000社\n- 予算売上：50,000,000円\n\n**実績**\n- 契約単価：9,500円/月（キャンペーン値引き）\n- 契約社数：5,200社\n- 実績売上：49,400,000円\n\n**差異分析**\n\n売上高差異 = 49,400,000円 - 50,000,000円 = -600,000円（不利差異）\n\n- **価格差異** = (9,500円 - 10,000円) × 5,200社 = -2,600,000円（不利）\n- **数量差異** = (5,200社 - 5,000社) × 10,000円 = 2,000,000円（有利）\n\n**結論**：値引きキャンペーンにより単価は下がったが、契約数は増加。ネットでは60万円の減収。\n\n### 原価差異の分解\n\n製造原価の差異を以下に分解します：\n\n1. **材料費差異**\n   - 価格差異 = (実際単価 - 標準単価) × 実際使用量\n   - 数量差異 = (実際使用量 - 標準使用量) × 標準単価\n\n2. **労務費差異**\n   - 賃率差異 = (実際賃率 - 標準賃率) × 実際作業時間\n   - 時間差異 = (実際作業時間 - 標準作業時間) × 標準賃率\n\n3. **経費差異**\n   - 予算差異\n   - 操業度差異（固定費の場合）\n\n### 具体例：システム開発プロジェクトの原価差異\n\n**予算**\n- SE単価：5,000円/時\n- 標準工数：1,000時間\n- 予算人件費：5,000,000円\n\n**実績**\n- SE単価：5,200円/時（ベテラン投入）\n- 実績工数：1,100時間（要件追加）\n- 実績人件費：5,720,000円\n\n**差異分析**\n\n人件費差異 = 5,720,000円 - 5,000,000円 = 720,000円（不利差異）\n\n- **賃率差異** = (5,200円 - 5,000円) × 1,100時間 = 220,000円（不利）\n- **時間差異** = (1,100時間 - 1,000時間) × 5,000円 = 500,000円（不利）\n\n**結論**：要件追加による工数増が主因（50万円）。ベテラン投入による単価上昇も影響（22万円）。\n\n## 予算管理のポイント\n\n### 1. 実現可能な予算設定\n\n高すぎる目標は意欲を削ぎ、低すぎる目標は成長を阻害します。\n\n### 2. タイムリーな情報提供\n\n月次決算を早期化し、迅速な対策を可能にします。\n\n### 3. 責任と権限の明確化\n\n予算達成の責任者と、必要な権限（人員配置、支出承認など）を明確にします。\n\n### 4. 柔軟な予算修正\n\n外部環境の大幅な変化（為替、法規制）に対しては、予算を修正します。\n\n### 5. 予算至上主義の回避\n\n予算達成のみを重視し、品質や顧客満足を犠牲にすることは避けます。\n\n## IT活用による予算管理の高度化\n\n### BIツールの活用\n\n- リアルタイムダッシュボードで予算進捗を可視化\n- ドリルダウン機能で詳細分析が容易\n- 予測分析による着地見込みの算出\n\n### クラウド会計システム\n\n- 部門別・プロジェクト別の予実管理\n- 経費精算との連携で実績の即時反映\n- モバイルアプリで外出先からも確認可能\n\nこれらのツールにより、予算管理の精度とスピードが飛躍的に向上します。"
    }
  ]
}
